README.rst
setup.py
bin/cmu_auth
cmu_auth/__init__.py
cmu_auth/auth.py
cmu_auth.egg-info/PKG-INFO
cmu_auth.egg-info/SOURCES.txt
cmu_auth.egg-info/dependency_links.txt
cmu_auth.egg-info/not-zip-safe
cmu_auth.egg-info/requires.txt
cmu_auth.egg-info/top_level.txt