Metadata-Version: 1.0
Name: cmu-auth
Version: 0.1.7
Summary: Simple python methods for authenticating to Carnegie Mellon Unversity services.
Home-page: https://github.com/willcrichton/cmu_auth
Author: Will Crichton
Author-email: willcrichton@cmu.edu
License: MIT
Platform: UNKNOWN
